MANIFEST.in
requirements.txt
setup.cfg
setup.py
pyFG/__init__.py
pyFG/ansible_helpers.py
pyFG/exceptions.py
pyFG/forticonfig.py
pyFG/fortios.py
pyFG/py23_compat.py
pyfg.egg-info/PKG-INFO
pyfg.egg-info/SOURCES.txt
pyfg.egg-info/dependency_links.txt
pyfg.egg-info/requires.txt
pyfg.egg-info/top_level.txt