Metadata-Version: 1.0
Name: pyfg
Version: 0.50
Summary: Python API for fortigate
Home-page: https://github.com/spotify/pyfg
Author: XNET
Author-email: lindblom+pyfg@spotify.com
License: UNKNOWN
Platform: UNKNOWN
